biomdp/__init__.py
biomdp/_version.py
biomdp/bikefitting_functions_utils.py
biomdp/biomec_xarray_accessor.py
biomdp/bland_altman_plot.py
biomdp/create_time_series.py
biomdp/filter_butter.py
biomdp/general_processing_functions.py
biomdp/image_pose.py
biomdp/jump_forces_utils.py
biomdp/nexus_functions_utils.py
biomdp/shannon_reconstruction.py
biomdp/slice_time_series_phases.py
biomdp/io/__init__.py
biomdp/io/read_isen_csv.py
biomdp/io/read_kistler_c3d.py
biomdp/io/read_kistler_txt.py
biomdp/io/read_noraxon_c3d.py
biomdp/io/read_noraxon_csv.py
biomdp/io/read_vicon_c3d.py
biomdp/io/read_vicon_csv.py
biomdp-0.7.27.dist-info/licenses/LICENSE
datasets/__init__.py
biomdp-0.7.27.dist-info/METADATA
biomdp-0.7.27.dist-info/WHEEL
biomdp-0.7.27.dist-info/top_level.txt
biomdp-0.7.27.dist-info/RECORD
