Metadata-Version: 2.4
Name: biomdp
Version: 0.7.27
Summary: Usefull set of functions for analyzing time series records, particularly for biomechanical data
Author-email: "Jose L. L. Elvira" <jose.lopeze@umh.es>
Project-URL: Homepage, https://github.com/joselvira/biomdp
Project-URL: Issues, https://github.com/joselvira/biomdp/issues
Keywords: biomechanics,biomecánica,data processing,time series,xarray
Classifier: Programming Language :: Python :: 3
Classifier: License :: OSI Approved :: MIT License
Classifier: Operating System :: OS Independent
Requires-Python: >=3.10
License-File: LICENSE
Dynamic: license-file
